tf2sku/__init__.py
tf2sku/skufy.py
tf2sku-0.1.1.dist-info/LICENSE.txt
tf2sku-0.1.1.dist-info/METADATA
tf2sku-0.1.1.dist-info/WHEEL
tf2sku-0.1.1.dist-info/top_level.txt
tf2sku-0.1.1.dist-info/RECORD
