Metadata-Version: 2.1
Name: tf2sku
Version: 0.1.1
Summary: Python lib for creating sku for tf2 items
Home-page: https://github.com/Jertusz/python-tf2-sku
Author: Jędrzej Szadejko
Author-email: shadyprywatny@gmail.com
License: MIT
Download-URL: https://github.com/Jertusz/python-tf2-sku/releases
Keywords: steam,trade,tf2,teamfortress2
Platform: UNKNOWN
Classifier: Development Status :: 3 - Alpha
